{
	"Type": "Live2D Expression",
	"FadeInTime": 0.15,
	"FadeOutTime": 0.15,
	"Parameters": [
		{
			"Id": "Paramcankaokaiguan",
			"Value": 17.971,
			"Blend": "Add"
		},
		{
			"Id": "Paramcankao",
			"Value": 0,
			"Blend": "Add"
		},
		{
			"Id": "Paramzuomeicuxi",
			"Value": 10.408,
			"Blend": "Add"
		},
		{
			"Id": "ParamBrowLY",
			"Value": 6.522,
			"Blend": "Add"
		},
		{
			"Id": "ParamBrowLX",
			"Value": 7.681,
			"Blend": "Add"
		},
		{
			"Id": "ParamBrowLAngle",
			"Value": 12.899,
			"Blend": "Add"
		},
		{
			"Id": "Param14",
			"Value": -20.145,
			"Blend": "Add"
		},
		{
			"Id": "Param15",
			"Value": -19.855,
			"Blend": "Add"
		},
		{
			"Id": "Paramzuomeigong",
			"Value": 33.061,
			"Blend": "Add"
		},
		{
			"Id": "ParamBrowRY",
			"Value": 2.464,
			"Blend": "Add"
		},
		{
			"Id": "ParamBrowRX",
			"Value": -9.42,
			"Blend": "Add"
		},
		{
			"Id": "ParamBrowRAngle",
			"Value": -18.696,
			"Blend": "Add"
		},
		{
			"Id": "Paramyoumeicuxi",
			"Value": 2.449,
			"Blend": "Add"
		},
		{
			"Id": "Param16",
			"Value": -15.507,
			"Blend": "Add"
		},
		{
			"Id": "Param17",
			"Value": -2.464,
			"Blend": "Add"
		},
		{
			"Id": "Paramyoumeigong",
			"Value": 28.776,
			"Blend": "Add"
		},
		{
			"Id": "Param3Lshangyanjian",
			"Value": -16.957,
			"Blend": "Add"
		},
		{
			"Id": "ParamEyeLOpen",
			"Value": 0,
			"Blend": "Add"
		},
		{
			"Id": "Param3Lxiayanjian",
			"Value": -19.565,
			"Blend": "Add"
		},
		{
			"Id": "Param3Lneiyanjiao",
			"Value": 5.362,
			"Blend": "Add"
		},
		{
			"Id": "Param3Lxiayanpi",
			"Value": 14.928,
			"Blend": "Add"
		},
		{
			"Id": "Param3Lwaiyanjiao",
			"Value": -7.391,
			"Blend": "Add"
		},
		{
			"Id": "ParamEyeROpen",
			"Value": 0,
			"Blend": "Add"
		},
		{
			"Id": "Param3Rshangyanjian",
			"Value": -23.913,
			"Blend": "Add"
		},
		{
			"Id": "Param3Rxiayanjian",
			"Value": -13.188,
			"Blend": "Add"
		},
		{
			"Id": "Param3Rneiyanjiao",
			"Value": 6.812,
			"Blend": "Add"
		},
		{
			"Id": "Param3Rwaiyanjiao",
			"Value": -2.754,
			"Blend": "Add"
		},
		{
			"Id": "Param3Rxiayanpi",
			"Value": -1.884,
			"Blend": "Add"
		},
		{
			"Id": "ParamEyeBallX",
			"Value": 0,
			"Blend": "Add"
		},
		{
			"Id": "ParamEyeBallY",
			"Value": -7.971,
			"Blend": "Add"
		},
		{
			"Id": "ParamREyeBallX",
			"Value": 0,
			"Blend": "Add"
		},
		{
			"Id": "Param2REyeBallY",
			"Value": -6.232,
			"Blend": "Add"
		},
		{
			"Id": "ParamMouthForm1",
			"Value": 0,
			"Blend": "Add"
		},
		{
			"Id": "Param10",
			"Value": 0,
			"Blend": "Add"
		},
		{
			"Id": "Param3Bizuibianxing2",
			"Value": -30,
			"Blend": "Add"
		},
		{
			"Id": "Param20zhoumeikaiguan",
			"Value": 0,
			"Blend": "Add"
		},
		{
			"Id": "Param3lianhongkaiguan",
			"Value": 0,
			"Blend": "Add"
		},
		{
			"Id": "Param3Rangsyanpi",
			"Value": 60,
			"Blend": "Add"
		},
		{
			"Id": "ParamMouthOpenY",
			"Value": 0,
			"Blend": "Add"
		},
		{
			"Id": "Paramyankuanghong",
			"Value": 60,
			"Blend": "Add"
		}
	]
}