{
  "Version": 3,
  "Name": "11901_F_c",
  "FileReferences": {
    "Moc": "11901_F_c.moc3",
    "Textures": [
      "textures/texture_00.png",
      "textures/texture_01.png"
    ],
    "Physics": "11901_F_c.physics3.json",
    "Pose": null,
    "DisplayInfo": "11901_F_c.cdi3.json",
    "Motions": {
      "full_2": [
        {
          "File": "motions/full_2.motion3.json"
        }
      ]
    },
    "Expressions": []
  },
  "Groups": [
    {
      "Target": "Parameter",
      "Name": "EyeBlink",
      "Ids": []
    },
    {
      "Target": "Parameter",
      "Name": "LipSync",
      "Ids": [
        "ParamMouthOpenY"
      ]
    }
  ]
}